pycolorise/__init__.py
pycolorise/base.py
pycolorise/constants.py
pycolorise/enums.py
pycolorise/styles.py
pycolorise/bgColors/__init__.py
pycolorise/bgColors/bright_colors.py
pycolorise/bgColors/normal_colors.py
pycolorise/colors/__init__.py
pycolorise/colors/bright_colors.py
pycolorise/colors/normal_colors.py
pycolorise-1.0.0.dist-info/LICENSE
pycolorise-1.0.0.dist-info/METADATA
pycolorise-1.0.0.dist-info/WHEEL
pycolorise-1.0.0.dist-info/top_level.txt
pycolorise-1.0.0.dist-info/RECORD
