Metadata-Version: 2.1
Name: pycolorise
Version: 1.0.0
Summary: Add colors to the terminal
Home-page: https://github.com/Modern-Realm/pycolorise
Author: P. Sai Keerthan Reddy
Author-email: saikeerthan.keerthan.9@gmail.com
License: MIT
Project-URL: Documentation, https://modern-realm.github.io/pycolorise/
Project-URL: Bug Tracker, https://github.com/Modern-Realm/pycolorise/issues
Project-URL: Examples, https://github.com/Modern-Realm/pycolorise/tree/main/Examples
Project-URL: Source, https://github.com/Modern-Realm/pycolorise/tree/main/package/pycolorise
Project-URL: Discord Server, https://discord.gg/GVMWx5EaAN
Keywords: colors,terminal colors,pycolorise
Classifier: Development Status :: 5 - Production/Stable
Classifier: Intended Audience :: Developers
Classifier: Programming Language :: Python :: 3.8
Classifier: License :: OSI Approved :: MIT License
Classifier: Operating System :: OS Independent
Classifier: Natural Language :: English
Classifier: Topic :: Internet
Classifier: Topic :: Software Development
Classifier: Topic :: Software Development :: Libraries
Classifier: Topic :: Software Development :: Libraries :: Python Modules
Classifier: Typing :: Typed
Requires-Python: >=3.7
License-File: LICENSE
